setup.py
dhconfiguratorv1/__init__.py
dhconfiguratorv1.egg-info/PKG-INFO
dhconfiguratorv1.egg-info/SOURCES.txt
dhconfiguratorv1.egg-info/dependency_links.txt
dhconfiguratorv1.egg-info/top_level.txt