Metadata-Version: 2.1
Name: dhconfiguratorv1
Version: 0.1
Summary: The funniest joke in the world
Home-page: http://github.com/danahynes/dhconfiguratorv1
Author: Dana Hynes
Author-email: danahynes@example.com
License: WTFPLv2
